AUTHORS
LICENSE
MANIFEST.in
README.md
requirements.txt
setup.py
django_smart_proxy.egg-info/PKG-INFO
django_smart_proxy.egg-info/SOURCES.txt
django_smart_proxy.egg-info/dependency_links.txt
django_smart_proxy.egg-info/requires.txt
django_smart_proxy.egg-info/top_level.txt
smart_proxy/__init__.py
smart_proxy/admin.py
smart_proxy/models.py
smart_proxy/urls.py
smart_proxy/views.py