Metadata-Version: 1.0
Name: django-smart-proxy
Version: 0.2.1
Summary: The django-smart-proxy app allows you to configure plug-and-play reverse proxy solutions for social networks and other complex integration points with your website.
Home-page: https://github.com/celerityweb/django-smart-proxy/
Author: Matt Caldwell
Author-email: matt.caldwell@gmail.com
License: MIT - see LICENSE file
Platform: UNKNOWN
